falcontyping/__init__.py
falcontyping/tests.py
falcontyping/base/__init__.py
falcontyping/base/exceptions.py
falcontyping/base/resource.py
falcontyping/base/utils.py
falcontyping/base/wrapper.py
falcontyping/middleware/__init__.py
falcontyping/middleware/typing_.py
falcontyping/typedjson/__init__.py
falcontyping/typedjson/annotation.py
falcontyping/typedjson/base.py
falcontyping/typedjson/decoding.py
falcontyping-0.7.0.dist-info/LICENSE
falcontyping-0.7.0.dist-info/METADATA
falcontyping-0.7.0.dist-info/WHEEL
falcontyping-0.7.0.dist-info/top_level.txt
falcontyping-0.7.0.dist-info/RECORD
