Metadata-Version: 2.1
Name: falcontyping
Version: 0.7.0
Summary: Add type hints support to Falcon with Pydantic and Marshmallow integration
Home-page: https://github.com/abdelrahman-t/falcontyping
Author: Abdurrahman Talaat <abdurrahman.talaat@gmail.com>
Author-email: abdurrahman.talaat@gmail.com
License: UNKNOWN
Project-URL: Documentation, https://github.com/abdelrahman-t/falcontyping
Keywords: falcon,typing,hints,mypy,pydantic,marshmallow
Platform: UNKNOWN
Classifier: Development Status :: 3 - Alpha
Classifier: Programming Language :: Python :: 3.7
Requires-Python: >=3.7.0
Requires-Dist: falcon
Requires-Dist: wrapt
